{
    "summary": [
        {
            "매출": 2513477000,
            "판관비": 1943375000,
            "당기순이익": 570102000,
            "예측매출": 3428639867,
            "예측판관비": 2666488000,
            "예측당기순이익": 762151867,
            "설명": "년도: 2022 - 매출: 2513477000, 판관비: 1943375000.0, 당기순이익: 570102000.0, 예측 매출: 3428639866.666748, 예측 판관비: 2666488000.0, 예측 당기순이익: 762151866.6666565"
        }
    ],
    "category_sales": [
        {
            "카테고리": "미분류",
            "실제공급가액": 210459000,
            "예측공급가액": 297249100,
            "설명": "2022년도 미분류 - 실제공급가액: 210459000, 예측공급가액: 297249100.0\n2022년도 블라우스 - 실제공급가액: 18875000, 예측공급가액: 338374500.0\n2022년도 스포츠웨어 - 실제공급가액: 404155000, 예측공급가액: 624139100.0\n2022년도 아우터 - 실제공급가액: 38137000, 예측공급가액: 102870400.0\n2022년도 원피스 - 실제공급가액: 36856000, 예측공급가액: 220942800.0\n2022년도 정장 - 실제공급가액: 1084652100, 예측공급가액: 1759109080.0\n2022년도 캐주얼 - 실제공급가액: 817100100, 예측공급가액: 470254120.0"
        },
        {
            "카테고리": "블라우스",
            "실제공급가액": 18875000,
            "예측공급가액": 338374500,
            "설명": "N/A"
        },
        {
            "카테고리": "스포츠웨어",
            "실제공급가액": 404155000,
            "예측공급가액": 624139100,
            "설명": "N/A"
        },
        {
            "카테고리": "아우터",
            "실제공급가액": 38137000,
            "예측공급가액": 102870400,
            "설명": "N/A"
        },
        {
            "카테고리": "원피스",
            "실제공급가액": 36856000,
            "예측공급가액": 220942800,
            "설명": "N/A"
        },
        {
            "카테고리": "정장",
            "실제공급가액": 1084652100,
            "예측공급가액": 1759109080,
            "설명": "N/A"
        },
        {
            "카테고리": "캐주얼",
            "실제공급가액": 817100100,
            "예측공급가액": 470254120,
            "설명": "N/A"
        }
    ],
    "gender_sales": [
        {
            "성별": "남",
            "실제공급가액": 1355596000,
            "예측공급가액": 1846673333,
            "설명": "2022년도 남 - 공급가액: 1355596000.0, 예측 공급가액: 1846673333.333374\n2022년도 여 - 공급가액: 1254638200.0, 예측 공급가액: 1710976133.333374"
        },
        {
            "성별": "여",
            "실제공급가액": 1254638200,
            "예측공급가액": 1710976133,
            "설명": "N/A"
        }
    ],
    "age_group_sales": [
        {
            "나이대": "10대",
            "실제공급가액": 0,
            "예측공급가액": 0,
            "설명": "2022년도 10대 - 공급가액: 0.0, 예측 공급가액: 0.0\n2022년도 20대 - 공급가액: 949329100.0, 예측 공급가액: 1289156466.666687\n2022년도 30대 - 공급가액: 1017886100.0, 예측 공급가액: 1395772666.666687\n2022년도 40대 - 공급가액: 643019000.0, 예측 공급가액: 872720333.333313"
        },
        {
            "나이대": "20대",
            "실제공급가액": 949329100,
            "예측공급가액": 1289156467,
            "설명": "N/A"
        },
        {
            "나이대": "30대",
            "실제공급가액": 1017886100,
            "예측공급가액": 1395772667,
            "설명": "N/A"
        },
        {
            "나이대": "40대",
            "실제공급가액": 643019000,
            "예측공급가액": 872720333,
            "설명": "N/A"
        }
    ],
    "vip_sales": [
        {
            "비율": "10%",
            "실제공급가액": 369101000,
            "예측공급가액": 442512972,
            "설명": "10% - 실제공급가액: 369101000.0, 예측공급가액: 442512971.8788061\n20% - 실제공급가액: 689633100.0, 예측공급가액: 826796981.2788204\n30% - 실제공급가액: 987155100.0, 예측공급가액: 1183494320.0000002"
        },
        {
            "비율": "20%",
            "실제공급가액": 689633100,
            "예측공급가액": 826796981,
            "설명": "N/A"
        },
        {
            "비율": "30%",
            "실제공급가액": 987155100,
            "예측공급가액": 1183494320,
            "설명": "N/A"
        }
    ],
    "area_sales": [
        {
            "지역": "산청군",
            "공급가액": 27425000,
            "예측공급가액": 30167500,
            "설명": "2022년도 산청군 - 공급가액: 27425000, 예측 공급가액: 30167500.000000004\n2022년도 서울특별시 종로구 - 공급가액: 23822000, 예측 공급가액: 26204200.000000004\n2022년도 서울특별시 동작구 - 공급가액: 23554000, 예측 공급가액: 25909400.000000004\n2022년도 군포시 - 공급가액: 22780000, 예측 공급가액: 25058000.000000004\n2022년도 부여군 - 공급가액: 22764000, 예측 공급가액: 25040400.000000004"
        },
        {
            "지역": "서울특별시 종로구",
            "공급가액": 23822000,
            "예측공급가액": 26204200,
            "설명": "N/A"
        },
        {
            "지역": "서울특별시 동작구",
            "공급가액": 23554000,
            "예측공급가액": 25909400,
            "설명": "N/A"
        },
        {
            "지역": "군포시",
            "공급가액": 22780000,
            "예측공급가액": 25058000,
            "설명": "N/A"
        },
        {
            "지역": "부여군",
            "공급가액": 22764000,
            "예측공급가액": 25040400,
            "설명": "N/A"
        }
    ]
}